{
   "requetes":[
      {
         "username":"COMPTE1",
         "token":"xxxxxxxxxxxxxx",
         "lien":"https://api.fr/",
         "survey_names":[
           "",
           "",
           "",
           "",
           "",
           "",
           ""
         ]
      },
      {
         "username":"COMPTE2",
         "token":"xxxxxxxxxxxxx",
         "lien":"https://autre_api.fr/",
         "survey_names":[
            "",
            "",
            "",
            "",
            "",
            "",
            ""
         ]
      },
      {
         "username":"ComptePro",
         "token":"xxxxxxxxxxxxxx",
         "lien":"https://API.fr/",
         "survey_names":[
            "",
            "",
            "",
            "",
            "",
            "",
            ""
         ]
      },
      {
         "username":"ComptePrive",
         "token":"xxxxxxxxxxx",
         "lien":"https://cs.API.net/",
         "survey_names":[
            "",
            "",
            "",
            "",
            "",
            "",
            ""
         ]
      }
   ]
}
